LICENSE
MANIFEST.in
README.rst
setup.py
django_formsetfield.egg-info/PKG-INFO
django_formsetfield.egg-info/SOURCES.txt
django_formsetfield.egg-info/dependency_links.txt
django_formsetfield.egg-info/top_level.txt
example/__init__.py
example/manage.py
example/settings.py
example/urls.py
example/orders/__init__.py
example/orders/forms.py
example/orders/urls.py
example/orders/views.py
formsetfield/__init__.py
formsetfield/fields.py
formsetfield/widgets.py
formsetfield/templates/formsetfield/formsetfield.html