Metadata-Version: 1.0
Name: django-formsetfield
Version: 0.1.1
Summary: Formsets inside forms
Home-page: https://github.com/yumike/django-formsetfield
Author: Mike Yumatov
Author-email: mike@yumatov.org
License: ISC
Platform: UNKNOWN
Classifier: Development Status :: 4 - Beta
Classifier: Framework :: Django
Classifier: Intended Audience :: Developers
Classifier: License :: OSI Approved :: ISC License (ISCL)
Classifier: Programming Language :: Python
Classifier: Programming Language :: Python :: 2.5
Classifier: Programming Language :: Python :: 2.6
Classifier: Programming Language :: Python :: 2.7
Classifier: Topic :: Internet :: WWW/HTTP
